README.rst
setup.py
jenkinshelper/__init__.py
jenkinshelper.egg-info/PKG-INFO
jenkinshelper.egg-info/SOURCES.txt
jenkinshelper.egg-info/dependency_links.txt
jenkinshelper.egg-info/requires.txt
jenkinshelper.egg-info/top_level.txt
jenkinshelper/log/__init__.py