Metadata-Version: 1.0
Name: jenkinshelper
Version: 1.1.1
Summary: Helper scripts for Jenkins written in Python 3
Home-page: https://github.com/jhasse/jenkinshelper
Author: Jan Niklas Hasse
Author-email: jhasse@bixense.com
License: UNKNOWN
Platform: UNKNOWN
